{
    "concepts": [], 
    "contentType": "Story", 
    "data": [
        "{}"
    ], 
    "description": "\u090f\u0915 \u091b\u094b\u091f\u0940 \u0938\u0940  \u0915\u0939\u093e\u0928\u0940 ", 
    "developer": "EkStep", 
    "domain": [
        "literacy"
    ], 
    "identifier": "domain_56990", 
    "imageTags": [
        "popuptint", 
        "btn ok highlights", 
        "story", 
        "icon home", 
        "icon submit", 
        "icon hint", 
        "retrybg", 
        "goodjobbg", 
        "icon reload", 
        "background", 
        "btn back", 
        "btn next"
    ], 
    "items": [
        "{}"
    ], 
    "language": [
        "Hindi"
    ], 
    "languageCode": "hi", 
    "mediaCount": {
        "gif": 0, 
        "jpg": 0, 
        "mp3": 4, 
        "ogg": 0, 
        "png": 14
    }, 
    "mp3Length": 17.36294784580499, 
    "mp3Transcription": {
        "/home/aditya/Downloads/EkStep/content2Vec/content2EnrichedJson/Data/domain_56990/assets/1464785780354retry_1460636610607": [], 
        "/home/aditya/Downloads/EkStep/content2Vec/content2EnrichedJson/Data/domain_56990/assets/1464785780678goodjob_1460636677521": [], 
        "/home/aditya/Downloads/EkStep/content2Vec/content2EnrichedJson/Data/domain_56990/assets/1464785782167p1_1464082184346": {
            "alternative": [
                {
                    "transcript": "Humpty Bhasha ki kitabe humpati Vigyan ki kitabe"
                }, 
                {
                    "transcript": "Humpty Bhasha ki kitabe Humpty Vigyan ki kitabe"
                }, 
                {
                    "transcript": "Humpty Bhasha ki kitabe humpati Vigyan Ki Kitab"
                }, 
                {
                    "transcript": "Humpty Bhasha ki kitabe Humpty Vigyan Ki Kitab"
                }, 
                {
                    "transcript": "Humpty Bhasha ki kitabe Humpty Vigyan ki kitaben"
                }
            ], 
            "final": true
        }, 
        "/home/aditya/Downloads/EkStep/content2Vec/content2EnrichedJson/Data/domain_56990/assets/1464785782487p2_1464082209278": {
            "alternative": [
                {
                    "confidence": 0.76797777, 
                    "transcript": "Humpty padna likhna humme Sakte Ganesh Thal karna"
                }, 
                {
                    "transcript": "Hum Sakte padna likhna humme Sakte Ganesh Thal karna"
                }, 
                {
                    "transcript": "Hum Sidhe padna likhna humme Sakte Ganesh Thal karna"
                }, 
                {
                    "transcript": "Hum Sabke padna likhna humme Sakte Ganesh Thal karna"
                }, 
                {
                    "transcript": "Humpty padna likhna humme Sakte Ganesh her karna"
                }
            ], 
            "final": true
        }
    }, 
    "owner": "239", 
    "tags": [
        "mela 3", 
        "pratham"
    ]
}