{
    "concepts": [], 
    "contentType": "Worksheet", 
    "data": [
        "{}"
    ], 
    "description": "\u092d\u093f\u0928\u094d\u0928 \u0905\u092d\u094d\u092f\u093e\u0938", 
    "developer": "EkStep", 
    "identifier": "domain_15300", 
    "imageTags": [
        "greenbox", 
        "page sel bg", 
        "icon home", 
        "icon submit", 
        "icon hint", 
        "speech bubble", 
        "yellowbox", 
        "isaksham", 
        "icon reload", 
        "background", 
        "icon next", 
        "icon previous"
    ], 
    "items": [
        "{}"
    ], 
    "language": [
        "Hindi"
    ], 
    "languageCode": "hi", 
    "mediaCount": {
        "gif": 0, 
        "jpg": 0, 
        "mp3": 0, 
        "ogg": 0, 
        "png": 12
    }, 
    "mp3Length": 0, 
    "mp3Transcription": {}, 
    "owner": "EkStep"
}